akasj/__init__.py
akasj/akasj.py
akasj/ceshi/__init__.py
akasj-0.0.3.dist-info/LICENSE
akasj-0.0.3.dist-info/METADATA
akasj-0.0.3.dist-info/WHEEL
akasj-0.0.3.dist-info/top_level.txt
akasj-0.0.3.dist-info/RECORD
