Metadata-Version: 2.1
Name: akasj
Version: 0.0.3
Summary: Hello Word
Author: ShiLuYao
License-File: LICENSE
